quantuloop/__init__.py
quantuloop/sparse/__init__.py
quantuloop/sparse/libquloop_sparse.so
quantuloop_sparse-0.1.1.dist-info/METADATA
quantuloop_sparse-0.1.1.dist-info/WHEEL
quantuloop_sparse-0.1.1.dist-info/top_level.txt
quantuloop_sparse-0.1.1.dist-info/RECORD
quantuloop_sparse.libs/libssl-2a9eae6f.so.1.0.2k
quantuloop_sparse.libs/libgssapi_krb5-497db0c6.so.2.2
quantuloop_sparse.libs/libselinux-0922c95c.so.1
quantuloop_sparse.libs/libql_sparse-972a1c21.so
quantuloop_sparse.libs/libgomp-a34b3233.so.1.0.0
quantuloop_sparse.libs/libcom_err-2abe824b.so.2.1
quantuloop_sparse.libs/libcrypto-19957f5b.so.1.0.2k
quantuloop_sparse.libs/libkrb5-fcafa220.so.3.3
quantuloop_sparse.libs/libk5crypto-b1f99d5c.so.3.1
quantuloop_sparse.libs/libkeyutils-dfe70bd6.so.1.5
quantuloop_sparse.libs/libpcre-9513aab5.so.1.2.0
quantuloop_sparse.libs/libkrb5support-d0bcff84.so.0.1
